{
  "source": "mock",
  "generatedAt": "2026-06-11T14:11:56.391Z",
  "sprint": {
    "number": 24,
    "week": "Jun 10, 2026",
    "totalShipped": 44,
    "totalShippedPrev": 41,
    "trend": "+3",
    "activeBlockers": 4,
    "blockersPastSla": 2,
    "infraAvgResponse": 26,
    "achSuccessRate": 98.4,
    "narrative": ""
  },
  "teams": [
    {
      "id": "infra",
      "name": "Infrastructure",
      "shortName": "INFRA",
      "board": "INFRA Board · Azure",
      "pm": "Shwetha P. (DevOps)",
      "systems": [
        "Azure",
        "GitHub Actions",
        "SQL Server",
        "MongoDB"
      ],
      "isCenter": true,
      "color": "#F5A623",
      "hexColor": 16098851,
      "health": "at-risk",
      "healthScore": 60,
      "healthBreakdown": {
        "base": 100,
        "sla": 0,
        "breaches": 0,
        "blockers": 0,
        "blockerCount": 0,
        "stalled": -40,
        "stalledRatio": 1,
        "wip": 0,
        "avgInFlightDays": 1.3,
        "velocity": 0,
        "velocityDelta": 0,
        "breachOverride": false
      },
      "shipped": 2,
      "inFlight": 4,
      "stalled": 0,
      "effortScore": 0.5,
      "effortLabel": "2/6 → Blocked",
      "standup": "Mon–Fri · 9:30 AM",
      "sprintPlanning": "Every other Monday · 1:30 PM",
      "blockers": [],
      "inFlightTickets": [
        {
          "id": "INFRA-891",
          "title": "LOX — HCM prod config for lender onboarding",
          "stage": "In Progress",
          "days": 2,
          "blocked": false
        },
        {
          "id": "INFRA-897",
          "title": "UWX — UWDE DB migration, new risk tier cols",
          "stage": "In Progress",
          "days": 1,
          "blocked": false
        },
        {
          "id": "INFRA-894",
          "title": "UWX — Ping Tree affiliate routing cloud config",
          "stage": "Queued",
          "days": 1,
          "blocked": false
        },
        {
          "id": "INFRA-902",
          "title": "AKX — Fabric pipeline for payment events",
          "stage": "Queued",
          "days": 1,
          "blocked": false
        }
      ],
      "shippedTickets": [
        {
          "id": "INFRA-880",
          "title": "Azure AKS cluster upgrade — node pool resize",
          "day": "Wed"
        },
        {
          "id": "INFRA-875",
          "title": "GitHub Actions runner pool scaling fix",
          "day": "Mon"
        }
      ],
      "teamsWaiting": 3,
      "openTickets": 4
    },
    {
      "id": "lo",
      "name": "Lending Ops",
      "shortName": "LO",
      "board": "LO Board · HCM",
      "pm": "Shruthi Chanthati",
      "systems": [
        "HCM (Hive Config Manager)",
        "LMS (Loan Management System)"
      ],
      "isCenter": false,
      "color": "#F5A623",
      "hexColor": 16098851,
      "health": "at-risk",
      "healthScore": 68,
      "healthBreakdown": {
        "base": 100,
        "sla": -15,
        "breaches": 1,
        "blockers": -6,
        "blockerCount": 1,
        "stalled": -13.3,
        "stalledRatio": 0.33,
        "wip": 0,
        "avgInFlightDays": 3,
        "velocity": 2.7,
        "velocityDelta": 0.27,
        "breachOverride": true
      },
      "shipped": 14,
      "inFlight": 6,
      "stalled": 2,
      "effortScore": 0.76,
      "effortLabel": "14/20 ↑ Good",
      "standup": "Mon/Tue/Wed/Fri · 9:00 AM",
      "sprintPlanning": "Every Thursday · 10:00 AM",
      "blockers": [
        {
          "ticketId": "LO-2041",
          "infraTicket": "INFRA-891",
          "assignee": "@Shwetha.p",
          "age": 36,
          "label": "LOX",
          "description": "HCM prod config — lender onboarding flow",
          "escalate": true,
          "slaState": "breach"
        }
      ],
      "inFlightTickets": [
        {
          "id": "LO-2041",
          "title": "HCM prod config — lender onboarding flow",
          "stage": "Ready to Deploy",
          "days": 3,
          "blocked": true
        },
        {
          "id": "LO-2038",
          "title": "HCM — Portfolio-level fee configuration",
          "stage": "In Dev",
          "days": 3
        },
        {
          "id": "LO-2039",
          "title": "LMS — Origination webhook retry logic",
          "stage": "In Code Review",
          "days": 2
        },
        {
          "id": "LO-2035",
          "title": "HCM — Lender permission matrix UI",
          "stage": "In QA",
          "days": 2
        },
        {
          "id": "LO-2044",
          "title": "Servicing screen — payment history edge case",
          "stage": "In Code Review",
          "days": 5
        }
      ],
      "shippedTickets": [
        {
          "id": "LO-2030",
          "title": "HCM — New lender profile configuration screen",
          "day": "Wed"
        },
        {
          "id": "LO-2033",
          "title": "LMS payment schedule display fix",
          "day": "Tue"
        },
        {
          "id": "LO-2025",
          "title": "HCM — Rate table bulk import tool",
          "day": "Mon"
        },
        {
          "id": "LO-2028",
          "title": "Loan origination audit log improvements",
          "day": "Mon"
        }
      ]
    },
    {
      "id": "pay",
      "name": "Payments",
      "shortName": "PAY",
      "board": "PAY Board · Explore Credit",
      "pm": "Mike O'Leary",
      "systems": [
        "Explore Credit",
        "MoneyComb",
        "USIO/NACHA ACH"
      ],
      "isCenter": false,
      "color": "#22C55E",
      "hexColor": 2278750,
      "health": "healthy",
      "healthScore": 92,
      "healthBreakdown": {
        "base": 100,
        "sla": 0,
        "breaches": 0,
        "blockers": 0,
        "blockerCount": 0,
        "stalled": -10,
        "stalledRatio": 0.25,
        "wip": 0,
        "avgInFlightDays": 2,
        "velocity": 2.2,
        "velocityDelta": 0.22,
        "breachOverride": false
      },
      "shipped": 11,
      "inFlight": 4,
      "stalled": 1,
      "effortScore": 0.8,
      "effortLabel": "11/15 ↑ Strong",
      "standup": "Mon–Wed · 8:30 AM",
      "sprintPlanning": "Every 2nd Friday · 8:30 AM",
      "blockers": [],
      "inFlightTickets": [
        {
          "id": "PAY-889",
          "title": "ACH retry logic — improved exponential backoff",
          "stage": "In Code Review",
          "days": 2
        },
        {
          "id": "PAY-891",
          "title": "Card payment fraud signal integration",
          "stage": "In Development",
          "days": 3
        },
        {
          "id": "PAY-885",
          "title": "Collections — delinquency tier logic update",
          "stage": "In QA",
          "days": 1
        },
        {
          "id": "PAY-892",
          "title": "NSF fee waiver automation — second-chance rule",
          "stage": "In Dev",
          "days": 2
        }
      ],
      "shippedTickets": [
        {
          "id": "PAY-880",
          "title": "ACH batch submission optimization",
          "day": "Thu"
        },
        {
          "id": "PAY-875",
          "title": "NSF fee waiver automation rule",
          "day": "Wed"
        },
        {
          "id": "PAY-872",
          "title": "MoneyComb — USIO webhook reliability fix",
          "day": "Tue"
        },
        {
          "id": "PAY-869",
          "title": "RCC processing timeout handling",
          "day": "Mon"
        }
      ]
    },
    {
      "id": "uw",
      "name": "UW / Lead Gen",
      "shortName": "UL",
      "board": "UL Board · VWF · UWDE",
      "pm": "Sanjana Umashankar",
      "systems": [
        "VWF (Verification Workflow)",
        "UWDE (Underwriting Data Engine)",
        "Ping Tree"
      ],
      "isCenter": false,
      "color": "#EF4444",
      "hexColor": 15680580,
      "health": "blocked",
      "healthScore": 36,
      "healthBreakdown": {
        "base": 100,
        "sla": -15,
        "breaches": 1,
        "blockers": -12,
        "blockerCount": 2,
        "stalled": -32,
        "stalledRatio": 0.8,
        "wip": -2,
        "avgInFlightDays": 4,
        "velocity": -3.1,
        "velocityDelta": -0.31,
        "breachOverride": true
      },
      "shipped": 9,
      "inFlight": 5,
      "stalled": 4,
      "effortScore": 0.62,
      "effortLabel": "9/14 ↓ Good",
      "standup": "Mon–Fri · 9:15 AM",
      "sprintPlanning": "Every 2nd Friday · 10:30 AM",
      "blockers": [
        {
          "ticketId": "UL-1105",
          "infraTicket": "INFRA-897",
          "assignee": "@Kevin Zhang",
          "age": 28,
          "label": "UWX",
          "description": "UWDE database migration — new risk tier cols",
          "escalate": true,
          "slaState": "warning"
        },
        {
          "ticketId": "UL-1089",
          "infraTicket": "INFRA-894",
          "assignee": "@Shwetha.p",
          "age": 22,
          "label": "UWX",
          "description": "Ping Tree cloud config — affiliate routing rules",
          "escalate": false,
          "slaState": "approaching"
        }
      ],
      "inFlightTickets": [
        {
          "id": "UL-1105",
          "title": "UWDE — New risk tier columns migration",
          "stage": "Ready for QA",
          "days": 4,
          "blocked": true
        },
        {
          "id": "UL-1089",
          "title": "Ping Tree — New affiliate cloud config",
          "stage": "Ready to Deploy",
          "days": 3,
          "blocked": true
        },
        {
          "id": "UL-1098",
          "title": "VWF — Score cutoff adjustment for HR segment",
          "stage": "Awaiting QA",
          "days": 4
        },
        {
          "id": "UL-1100",
          "title": "UWDE — PDP (Payday Predictor) v2 model",
          "stage": "In Code Review",
          "days": 7
        },
        {
          "id": "UL-1092",
          "title": "Ping Tree routing v2 — priority algorithm update",
          "stage": "Analysis Done",
          "days": 2
        }
      ],
      "shippedTickets": [
        {
          "id": "UL-1090",
          "title": "VWF — Document verification timeout fix",
          "day": "Thu"
        },
        {
          "id": "UL-1085",
          "title": "Ping Tree — Affiliate routing priority update",
          "day": "Mon"
        }
      ]
    },
    {
      "id": "analytics",
      "name": "Analytics",
      "shortName": "ANA",
      "board": "MS Fabric · ExploreLMS",
      "pm": "Ben Lull (Principal Architect)",
      "systems": [
        "MS Fabric",
        "ExploreLMSReplica",
        "Azure DevOps",
        "SQL Server"
      ],
      "isCenter": false,
      "color": "#22C55E",
      "hexColor": 16098851,
      "health": "healthy",
      "healthScore": 84,
      "healthBreakdown": {
        "base": 100,
        "sla": 0,
        "breaches": 0,
        "blockers": -6,
        "blockerCount": 1,
        "stalled": -13.3,
        "stalledRatio": 0.33,
        "wip": 0,
        "avgInFlightDays": 2.3,
        "velocity": 3.3,
        "velocityDelta": 0.33,
        "breachOverride": false
      },
      "shipped": 8,
      "inFlight": 3,
      "stalled": 1,
      "effortScore": 0.78,
      "effortLabel": "8/11 ↑ Good",
      "standup": "Mon–Fri · 9:00 AM EST",
      "sprintPlanning": "Every 2nd Thursday · 11:00 AM",
      "blockers": [
        {
          "ticketId": "ANA-340",
          "infraTicket": "INFRA-902",
          "assignee": "@Kevin Zhang",
          "age": 18,
          "label": "AKX",
          "description": "Fabric pipeline for new payment events source",
          "escalate": false,
          "slaState": "approaching"
        }
      ],
      "inFlightTickets": [
        {
          "id": "ANA-340",
          "title": "Fabric pipeline — new payment events source",
          "stage": "Blocked on Infra",
          "days": 2,
          "blocked": true
        },
        {
          "id": "ANA-338",
          "title": "Fabric silver layer sync — origination events",
          "stage": "In Code Review",
          "days": 3
        },
        {
          "id": "ANA-335",
          "title": "NSF rate dashboard — segment breakdown by LR/HR",
          "stage": "In Dev",
          "days": 2
        }
      ],
      "shippedTickets": [
        {
          "id": "ANA-330",
          "title": "Q2 vintage performance — LO + FPD cohort analysis",
          "day": "Thu"
        },
        {
          "id": "ANA-325",
          "title": "NSF rate trend — segment breakdown",
          "day": "Wed"
        },
        {
          "id": "ANA-318",
          "title": "Lead Gen conversion funnel — affiliate quality report",
          "day": "Tue"
        }
      ]
    }
  ],
  "infraBlockers": [
    {
      "ticketId": "LO-2041",
      "infraTicket": "INFRA-891",
      "assignee": "@Shwetha.p",
      "age": 36,
      "label": "LOX",
      "description": "HCM prod config — lender onboarding flow",
      "escalate": true,
      "slaState": "breach",
      "teamId": "lo",
      "teamName": "Lending Ops"
    },
    {
      "ticketId": "UL-1105",
      "infraTicket": "INFRA-897",
      "assignee": "@Kevin Zhang",
      "age": 28,
      "label": "UWX",
      "description": "UWDE database migration — new risk tier cols",
      "escalate": true,
      "slaState": "warning",
      "teamId": "uw",
      "teamName": "UW / Lead Gen"
    },
    {
      "ticketId": "UL-1089",
      "infraTicket": "INFRA-894",
      "assignee": "@Shwetha.p",
      "age": 22,
      "label": "UWX",
      "description": "Ping Tree cloud config — affiliate routing rules",
      "escalate": false,
      "slaState": "approaching",
      "teamId": "uw",
      "teamName": "UW / Lead Gen"
    },
    {
      "ticketId": "ANA-340",
      "infraTicket": "INFRA-902",
      "assignee": "@Kevin Zhang",
      "age": 18,
      "label": "AKX",
      "description": "Fabric pipeline for new payment events source",
      "escalate": false,
      "slaState": "approaching",
      "teamId": "analytics",
      "teamName": "Analytics"
    }
  ],
  "ceremonies": [
    {
      "name": "Daily Standup — Payments",
      "team": "pay",
      "time": "8:30 AM",
      "state": "done"
    },
    {
      "name": "Daily Standup — Lending Ops",
      "team": "lo",
      "time": "9:00 AM",
      "state": "done"
    },
    {
      "name": "Daily Standup — Analytics",
      "team": "analytics",
      "time": "9:00 AM",
      "state": "done"
    },
    {
      "name": "Daily Standup — UW / Lead Gen",
      "team": "uw",
      "time": "9:15 AM",
      "state": "done"
    },
    {
      "name": "Daily Standup — Infrastructure",
      "team": "infra",
      "time": "9:30 AM",
      "state": "done"
    }
  ],
  "lifecycle": [
    {
      "id": "UL-1105",
      "teamId": "uw",
      "title": "UWDE — New risk tier columns migration",
      "stage": "Ready for QA",
      "stageIndex": 6,
      "days": 4,
      "blocked": true,
      "stages": [
        {
          "label": "Ready for Analysis",
          "state": "done"
        },
        {
          "label": "In Analysis",
          "state": "done"
        },
        {
          "label": "Ready for Dev",
          "state": "done"
        },
        {
          "label": "In Dev",
          "state": "done"
        },
        {
          "label": "Code Review",
          "state": "done"
        },
        {
          "label": "Dev Done",
          "state": "done"
        },
        {
          "label": "In QA",
          "state": "blocked"
        },
        {
          "label": "QA Done",
          "state": "pending"
        },
        {
          "label": "Ready to Deploy",
          "state": "pending"
        },
        {
          "label": "Done",
          "state": "pending"
        }
      ]
    },
    {
      "id": "LO-2041",
      "teamId": "lo",
      "title": "HCM prod config — lender onboarding flow",
      "stage": "Ready to Deploy",
      "stageIndex": 8,
      "days": 3,
      "blocked": true,
      "stages": [
        {
          "label": "Ready for Analysis",
          "state": "done"
        },
        {
          "label": "In Analysis",
          "state": "done"
        },
        {
          "label": "Ready for Dev",
          "state": "done"
        },
        {
          "label": "In Dev",
          "state": "done"
        },
        {
          "label": "Code Review",
          "state": "done"
        },
        {
          "label": "Dev Done",
          "state": "done"
        },
        {
          "label": "In QA",
          "state": "done"
        },
        {
          "label": "QA Done",
          "state": "done"
        },
        {
          "label": "Ready to Deploy",
          "state": "blocked"
        },
        {
          "label": "Done",
          "state": "pending"
        }
      ]
    },
    {
      "id": "UL-1089",
      "teamId": "uw",
      "title": "Ping Tree — New affiliate cloud config",
      "stage": "Ready to Deploy",
      "stageIndex": 8,
      "days": 3,
      "blocked": true,
      "stages": [
        {
          "label": "Ready for Analysis",
          "state": "done"
        },
        {
          "label": "In Analysis",
          "state": "done"
        },
        {
          "label": "Ready for Dev",
          "state": "done"
        },
        {
          "label": "In Dev",
          "state": "done"
        },
        {
          "label": "Code Review",
          "state": "done"
        },
        {
          "label": "Dev Done",
          "state": "done"
        },
        {
          "label": "In QA",
          "state": "done"
        },
        {
          "label": "QA Done",
          "state": "done"
        },
        {
          "label": "Ready to Deploy",
          "state": "blocked"
        },
        {
          "label": "Done",
          "state": "pending"
        }
      ]
    },
    {
      "id": "ANA-340",
      "teamId": "analytics",
      "title": "Fabric pipeline — new payment events source",
      "stage": "Blocked on Infra",
      "stageIndex": 0,
      "days": 2,
      "blocked": true,
      "stages": [
        {
          "label": "Ready for Analysis",
          "state": "blocked"
        },
        {
          "label": "In Analysis",
          "state": "pending"
        },
        {
          "label": "Ready for Dev",
          "state": "pending"
        },
        {
          "label": "In Dev",
          "state": "pending"
        },
        {
          "label": "Code Review",
          "state": "pending"
        },
        {
          "label": "Dev Done",
          "state": "pending"
        },
        {
          "label": "In QA",
          "state": "pending"
        },
        {
          "label": "QA Done",
          "state": "pending"
        },
        {
          "label": "Ready to Deploy",
          "state": "pending"
        },
        {
          "label": "Done",
          "state": "pending"
        }
      ]
    }
  ],
  "initiatives": [
    {
      "id": "LO-2000",
      "teamId": "lo",
      "name": "Lender Onboarding Revamp",
      "progressPct": 43,
      "doneChildren": 6,
      "totalChildren": 14,
      "blockedChildren": 1,
      "status": "blocked",
      "expectedPct": 60
    },
    {
      "id": "PAY-800",
      "teamId": "pay",
      "name": "ACH Reliability Hardening",
      "progressPct": 80,
      "doneChildren": 8,
      "totalChildren": 10,
      "blockedChildren": 0,
      "status": "on-track",
      "expectedPct": 60
    },
    {
      "id": "UL-1000",
      "teamId": "uw",
      "name": "UWDE Risk Tier Migration",
      "progressPct": 25,
      "doneChildren": 3,
      "totalChildren": 12,
      "blockedChildren": 2,
      "status": "blocked",
      "expectedPct": 60
    },
    {
      "id": "UL-1050",
      "teamId": "uw",
      "name": "Ping Tree Routing v2",
      "progressPct": 63,
      "doneChildren": 5,
      "totalChildren": 8,
      "blockedChildren": 0,
      "status": "on-track",
      "expectedPct": 60
    },
    {
      "id": "ANA-300",
      "teamId": "analytics",
      "name": "Q2 Vintage Analytics Suite",
      "progressPct": 82,
      "doneChildren": 9,
      "totalChildren": 11,
      "blockedChildren": 0,
      "status": "on-track",
      "expectedPct": 60
    },
    {
      "id": "INFRA-850",
      "teamId": "infra",
      "name": "Platform Hardening Q2",
      "progressPct": 44,
      "doneChildren": 4,
      "totalChildren": 9,
      "blockedChildren": 0,
      "status": "at-risk",
      "expectedPct": 60
    }
  ],
  "ticker": [
    "Lending Ops: LO-2041 blocked on INFRA-891 — 36h, exceeds SLA",
    "UW / Lead Gen: UL-1105 blocked on INFRA-897 — 28h, exceeds SLA",
    "UL-1089 waiting on INFRA-894 — 22h",
    "ANA-340 waiting on INFRA-902 — 18h",
    "Lending Ops leads with 14 shipped this sprint",
    "Sprint 24: 44 shipped (+3 vs last)",
    "Infra avg response 26h · 2 past SLA",
    "ACH success rate 98.4%",
    "UW / Lead Gen flagged BLOCKED — health 36/100"
  ],
  "hash": "fcda2c10ce3a"
}
